README
setup.py
lockdown/__init__.py
lockdown/bin.py
lockdown.egg-info/PKG-INFO
lockdown.egg-info/SOURCES.txt
lockdown.egg-info/dependency_links.txt
lockdown.egg-info/entry_points.txt
lockdown.egg-info/requires.txt
lockdown.egg-info/top_level.txt