Metadata-Version: 1.1
Name: lockdown
Version: 0.4.0
Summary: An un-audited security tool to encrypt Python code.
Home-page: https://bitbucket.org/johannestaas/lockdown
Author: Johan Nestaas
Author-email: johannestaas@gmail.com
License: BSD
Keywords: crypto cryptography security source code
Platform: UNKNOWN
Classifier: Development Status :: 4 - Beta
Classifier: Topic :: Utilities
Classifier: License :: OSI Approved :: BSD License
Classifier: Intended Audience :: Developers
Classifier: Environment :: Console
Classifier: Operating System :: MacOS :: MacOS X
Classifier: Operating System :: Microsoft :: Windows
Classifier: Operating System :: POSIX
Classifier: Programming Language :: Python
Classifier: Topic :: Software Development
Classifier: Topic :: System :: Software Distribution
